{
    "user": [
        {
            "ClientId": 3,
            "Email": "bambang@qoin.id",
            "EmailConfirmed": true,
            "Fullname": "BAMBANG PRASETYO",
            "Id": 1538,
            "NIK": "3312122711850001",
            "NIKConfirmed": false,
            "Phone": "6281328637400",
            "PhoneConfirmed": true,
            "Source": "app",
            "Status": 1
        },
        {
            "ClientId": 3,
            "Email": "kenichi@loyalto.id",
            "EmailConfirmed": true,
            "Fullname": "KENTZY",
            "Id": 1547,
            "NIK": "",
            "NIKConfirmed": false,
            "Phone": "6281386550435",
            "PhoneConfirmed": true,
            "Source": "app",
            "Status": 1
        },
        {
            "ClientId": 3,
            "Email": "netoya93@gmail.com",
            "EmailConfirmed": true,
            "Fullname": "NETY HERAWATY",
            "Id": 1552,
            "NIK": "3507066808900001",
            "NIKConfirmed": true,
            "Phone": "628111116467",
            "PhoneConfirmed": true,
            "Source": "app",
            "Status": 1
        },
        {
            "ClientId": 3,
            "Email": "yadisty24@gmail.com",
            "EmailConfirmed": true,
            "Fullname": "YADI SETIYADI",
            "Id": 1577,
            "NIK": "3201372402960001",
            "NIKConfirmed": true,
            "Phone": "6281315151996",
            "PhoneConfirmed": true,
            "Source": "app",
            "Status": 0
        },
        {
            "ClientId": 3,
            "Email": "vyona@qoin.id",
            "EmailConfirmed": true,
            "Fullname": "vyona",
            "Id": 1606,
            "NIK": null,
            "NIKConfirmed": false,
            "Phone": "6281311053950",
            "PhoneConfirmed": true,
            "Source": "app",
            "Status": 1
        },
        {
            "ClientId": 3,
            "Email": "liza@loyalto.id",
            "EmailConfirmed": true,
            "Fullname": "LIZA APRILIYANI",
            "Id": 1612,
            "NIK": "3212286804990003",
            "NIKConfirmed": true,
            "Phone": "6285320842870",
            "PhoneConfirmed": true,
            "Source": "app",
            "Status": 1
        },
        {
            "ClientId": 3,
            "Email": "pearlmaknun6@gmail.com",
            "EmailConfirmed": true,
            "Fullname": "AQILA FATHIMAH AZZAHRA",
            "Id": 1614,
            "NIK": "",
            "NIKConfirmed": false,
            "Phone": "6285971776760",
            "PhoneConfirmed": true,
            "Source": "app",
            "Status": 1
        },
        {
            "ClientId": 3,
            "Email": "ilyas@loyalto.id",
            "EmailConfirmed": true,
            "Fullname": "Muhammad Ilyas",
            "Id": 1617,
            "NIK": "9998887772221143",
            "NIKConfirmed": true,
            "Phone": "6282269616558",
            "PhoneConfirmed": true,
            "Source": "web",
            "Status": 1
        },
        {
            "ClientId": 3,
            "Email": "adminlv2@loyalto.id",
            "EmailConfirmed": true,
            "Fullname": "Admin LvDua",
            "Id": 1618,
            "NIK": "3877222209872345",
            "NIKConfirmed": false,
            "Phone": "628771212121",
            "PhoneConfirmed": true,
            "Source": "web",
            "Status": 1
        },
        {
            "ClientId": 3,
            "Email": "adminlv3@loyalto.id",
            "EmailConfirmed": true,
            "Fullname": "Admin LvTiga",
            "Id": 1619,
            "NIK": "9772129992120001",
            "NIKConfirmed": false,
            "Phone": "7712212122",
            "PhoneConfirmed": true,
            "Source": "web",
            "Status": 1
        },
        {
            "ClientId": 3,
            "Email": "adminlv3_2@loyalto.id",
            "EmailConfirmed": true,
            "Fullname": "Admin LvTiga_2",
            "Id": 1620,
            "NIK": "1277233398721281",
            "NIKConfirmed": false,
            "Phone": "66677782122",
            "PhoneConfirmed": true,
            "Source": "web",
            "Status": 1
        },
        {
            "ClientId": 3,
            "Email": "yustan@loyalto.id",
            "EmailConfirmed": true,
            "Fullname": "Farhan Martiyansyah",
            "Id": 1622,
            "NIK": "3201313103970004",
            "NIKConfirmed": true,
            "Phone": "628988594846",
            "PhoneConfirmed": true,
            "Source": "app",
            "Status": 1
        },
        {
            "ClientId": 3,
            "Email": "mahajir@loyalto.id",
            "EmailConfirmed": true,
            "Fullname": "MAHAJIR TAQARRUB",
            "Id": 1627,
            "NIK": "3275030506960027",
            "NIKConfirmed": true,
            "Phone": "6281298745715",
            "PhoneConfirmed": true,
            "Source": "app",
            "Status": 1
        },
        {
            "ClientId": 3,
            "Email": null,
            "EmailConfirmed": false,
            "Fullname": null,
            "Id": 1628,
            "NIK": null,
            "NIKConfirmed": false,
            "Phone": "6282148223997",
            "PhoneConfirmed": true,
            "Source": "app",
            "Status": 1
        },
        {
            "ClientId": 3,
            "Email": "arini@loyalto.id",
            "EmailConfirmed": true,
            "Fullname": "THORJIMAN ODINSON",
            "Id": 1631,
            "NIK": "3522125010990001",
            "NIKConfirmed": true,
            "Phone": "6282335850305",
            "PhoneConfirmed": true,
            "Source": "app",
            "Status": 1
        },
        {
            "ClientId": 3,
            "Email": "fkurniawan64@gmail.com",
            "EmailConfirmed": true,
            "Fullname": "FANDY KURNIAWAN",
            "Id": 1632,
            "NIK": "3216061304920028",
            "NIKConfirmed": true,
            "Phone": "628111828273",
            "PhoneConfirmed": true,
            "Source": "app",
            "Status": 1
        },
        {
            "ClientId": 3,
            "Email": "mahajir@pointo.id",
            "EmailConfirmed": true,
            "Fullname": "Hariyadi,st",
            "Id": 1635,
            "NIK": "7308232505910001",
            "NIKConfirmed": true,
            "Phone": "6285760648854",
            "PhoneConfirmed": true,
            "Source": "app",
            "Status": 1
        },
        {
            "ClientId": 3,
            "Email": null,
            "EmailConfirmed": false,
            "Fullname": null,
            "Id": 1639,
            "NIK": null,
            "NIKConfirmed": false,
            "Phone": "6285159335715",
            "PhoneConfirmed": true,
            "Source": "app",
            "Status": 1
        },
        {
            "ClientId": 3,
            "Email": "lizaapriliyani99@gmail.com",
            "EmailConfirmed": false,
            "Fullname": "Test",
            "Id": 1641,
            "NIK": "3212284806665003",
            "NIKConfirmed": false,
            "Phone": "6285694486712",
            "PhoneConfirmed": false,
            "Source": "web",
            "Status": 1
        },
        {
            "ClientId": 3,
            "Email": "testNTT@gmail.com",
            "EmailConfirmed": true,
            "Fullname": "testing",
            "Id": 1642,
            "NIK": null,
            "NIKConfirmed": false,
            "Phone": "6281387997511",
            "PhoneConfirmed": true,
            "Source": "app",
            "Status": 1
        },
        {
            "ClientId": 3,
            "Email": "lulu@loyalto.id",
            "EmailConfirmed": true,
            "Fullname": "AQILA FATIMAH AZZAHRA",
            "Id": 1644,
            "NIK": "3310055802020003",
            "NIKConfirmed": true,
            "Phone": "6287820989742",
            "PhoneConfirmed": true,
            "Source": "app",
            "Status": 1
        },
        {
            "ClientId": 3,
            "Email": "pearlmaknun1@gmail.com",
            "EmailConfirmed": true,
            "Fullname": null,
            "Id": 1645,
            "NIK": null,
            "NIKConfirmed": false,
            "Phone": "628569034593",
            "PhoneConfirmed": true,
            "Source": "app",
            "Status": 1
        }
    ]
}